README.rst
setup.py
buildbot_dbconfig/VERSION
buildbot_dbconfig/__init__.py
buildbot_dbconfig/api.py
buildbot_dbconfig.egg-info/PKG-INFO
buildbot_dbconfig.egg-info/SOURCES.txt
buildbot_dbconfig.egg-info/dependency_links.txt
buildbot_dbconfig.egg-info/entry_points.txt
buildbot_dbconfig.egg-info/requires.txt
buildbot_dbconfig.egg-info/top_level.txt
buildbot_dbconfig/static/scripts.js
buildbot_dbconfig/static/scripts.js.map
buildbot_dbconfig/static/styles.css
buildbot_dbconfig/static/tests.js